<!DOCTYPE qgis_style>
<qgis_style version="1">
  <symbols>
    <symbol name="25.001: Contact, planetary - Location accurate" alpha="1" force_rhr="0" type="line" clip_to_extent="1" tags="fgdc">
      <layer locked="0" enabled="1" class="SimpleLine" pass="0">
        <prop k="capstyle" v="square"/>
        <prop k="customdash" v="5;2"/>
        <prop k="customdash_map_unit_scale" v="3x:0,0,0,0,0,0"/>
        <prop k="customdash_unit" v="MM"/>
        <prop k="draw_inside_polygon" v="0"/>
        <prop k="joinstyle" v="bevel"/>
        <prop k="line_color" v="0,0,0,255"/>
        <prop k="line_style" v="solid"/>
        <prop k="line_width" v="0.15"/>
        <prop k="line_width_unit" v="MM"/>
        <prop k="offset" v="0"/>
        <prop k="offset_map_unit_scale" v="3x:0,0,0,0,0,0"/>
        <prop k="offset_unit" v="MM"/>
        <prop k="ring_filter" v="0"/>
        <prop k="use_custom_dash" v="0"/>
        <prop k="width_map_unit_scale" v="3x:0,0,0,0,0,0"/>
        <data_defined_properties>
          <Option type="Map">
            <Option value="" name="name" type="QString"/>
            <Option name="properties"/>
            <Option value="collection" name="type" type="QString"/>
          </Option>
        </data_defined_properties>
      </layer>
    </symbol>
  </symbols>
  <colorramps/>
</qgis_style>
